spcc_tools/__init__.py
spcc_tools/assembler/__init__.py
spcc_tools/assembler/two_pass.py
spcc_tools/cfg/__init__.py
spcc_tools/cfg/first.py
spcc_tools/cfg/follow.py
spcc_tools/lexical/__init__.py
spcc_tools/lexical/counter.py
spcc_tools/macro/__init__.py
spcc_tools/macro/expander.py
spcc_tools-0.1.0.dist-info/licenses/LICENSE
spcc_tools-0.1.0.dist-info/METADATA
spcc_tools-0.1.0.dist-info/WHEEL
spcc_tools-0.1.0.dist-info/entry_points.txt
spcc_tools-0.1.0.dist-info/top_level.txt
spcc_tools-0.1.0.dist-info/RECORD
