Metadata-Version: 2.4
Name: spcc-tools
Version: 0.1.0
Summary: System Programming and Compiler Construction tools and experiments
Home-page: https://github.com/yourusername/spcc-tools
Author: Vivek Yadav
Author-email: example@example.com
Classifier: Programming Language :: Python :: 3
Classifier: License :: OSI Approved :: MIT License
Classifier: Operating System :: OS Independent
Requires-Python: >=3.6
License-File: LICENSE
Requires-Dist: ply
Dynamic: author
Dynamic: author-email
Dynamic: classifier
Dynamic: description
Dynamic: description-content-type
Dynamic: home-page
Dynamic: license-file
Dynamic: requires-dist
Dynamic: requires-python
Dynamic: summary
